<annotation>
	<folder>Plagueofsource</folder>
	<filename>000353.jpg</filename>
	<path>E:\Plagueofsource\000353.jpg</path>
	<source>
		<database>Unknown</database>
	</source>
	<size>
		<width>800</width>
		<height>600</height>
		<depth>3</depth>
	</size>
	<segmented>0</segmented>
	<object>
		<name>StormRider</name>
		<pose>Unspecified</pose>
		<truncated>0</truncated>
		<difficult>0</difficult>
		<bndbox>
			<xmin>328</xmin>
			<ymin>305</ymin>
			<xmax>374</xmax>
			<ymax>401</ymax>
		</bndbox>
	</object>
	<object>
		<name>WhitehairedBanshee</name>
		<pose>Unspecified</pose>
		<truncated>0</truncated>
		<difficult>0</difficult>
		<bndbox>
			<xmin>455</xmin>
			<ymin>304</ymin>
			<xmax>507</xmax>
			<ymax>420</ymax>
		</bndbox>
	</object>
	<object>
		<name>WhitehairedBanshee</name>
		<pose>Unspecified</pose>
		<truncated>0</truncated>
		<difficult>0</difficult>
		<bndbox>
			<xmin>574</xmin>
			<ymin>332</ymin>
			<xmax>629</xmax>
			<ymax>438</ymax>
		</bndbox>
	</object>
	<object>
		<name>WhitehairedBanshee</name>
		<pose>Unspecified</pose>
		<truncated>0</truncated>
		<difficult>0</difficult>
		<bndbox>
			<xmin>637</xmin>
			<ymin>330</ymin>
			<xmax>711</xmax>
			<ymax>438</ymax>
		</bndbox>
	</object>
</annotation>